{
    "type": "static",
    "backgroundColor": "#0F172A",
    "logo": {
        "src": "",
        "width": 150,
        "height": 150,
        "animation": "none"
    },
    "lottie": {
        "src": "",
        "width": 300,
        "height": 300,
        "loop": false,
        "autoPlay": false
    },
    "text": {
        "content": "",
        "color": "#FFFFFF",
        "fontSize": 16,
        "animation": "none"
    },
    "duration": 500,
    "transition": "fade",
    "autoHide": true
}